USB_Quartermaster_SSH/__init__.py
USB_Quartermaster_SSH/communicator.py
usb_quartermaster_ssh-0.1.0.dist-info/WHEEL
usb_quartermaster_ssh-0.1.0.dist-info/METADATA
usb_quartermaster_ssh-0.1.0.dist-info/RECORD
