Metadata-Version: 2.1
Name: usb-quartermaster-ssh
Version: 0.1.0
Summary: Support for Quartermaster to communicate with remote hosts over SSH
Author: Tim Laurence
Author-email: timdaman@gmail.com
Requires-Python: >=3.7,<4.0
Classifier: Programming Language :: Python :: 3
Classifier: Programming Language :: Python :: 3.7
Classifier: Programming Language :: Python :: 3.8
Requires-Dist: USB_Quartermaster_common (>=0.1.0,<0.2.0)
